odoo/addons/website_sale_permit_extra_info/LICENSE
odoo/addons/website_sale_permit_extra_info/README.rst
odoo/addons/website_sale_permit_extra_info/__init__.py
odoo/addons/website_sale_permit_extra_info/__manifest__.py
odoo/addons/website_sale_permit_extra_info/controllers/__init__.py
odoo/addons/website_sale_permit_extra_info/controllers/website.py
odoo/addons/website_sale_permit_extra_info/images/screen.png
odoo/addons/website_sale_permit_extra_info/models/__init__.py
odoo/addons/website_sale_permit_extra_info/readme/CONTRIBUTORS.md
odoo/addons/website_sale_permit_extra_info/readme/DESCRIPTION.md
odoo/addons/website_sale_permit_extra_info/readme/USAGE.md
odoo/addons/website_sale_permit_extra_info/security/security.xml
odoo/addons/website_sale_permit_extra_info/static/description/icon.png
odoo/addons/website_sale_permit_extra_info/static/description/index.html
odoo/addons/website_sale_permit_extra_info/views/website_templates.xml
odoo_addon_website_sale_permit_extra_info-18.0.1.0.0.dist-info/METADATA
odoo_addon_website_sale_permit_extra_info-18.0.1.0.0.dist-info/WHEEL
odoo_addon_website_sale_permit_extra_info-18.0.1.0.0.dist-info/top_level.txt
odoo_addon_website_sale_permit_extra_info-18.0.1.0.0.dist-info/RECORD
